igittigitt/__init__.py
igittigitt/__init__conf__.py
igittigitt/conf_igittigitt.py
igittigitt/igittigitt.py
igittigitt/igittigitt_cli.py
igittigitt/py.typed
igittigitt-2.1.5.dist-info/LICENSE
igittigitt-2.1.5.dist-info/METADATA
igittigitt-2.1.5.dist-info/WHEEL
igittigitt-2.1.5.dist-info/entry_points.txt
igittigitt-2.1.5.dist-info/top_level.txt
igittigitt-2.1.5.dist-info/RECORD
